{
    "Translation": "NKJV",
    "group": "POETRY \u0026 WINSDOM",
    "BookName": "Psalms ",
    "BookNumber": 19,
    "Audio": [],
    "Content": "\n\u003cdiv class=\"title\"\u003e\u003ch1\u003e81\u003c/h1\u003e\u003ch3\u003eAn Appeal for Israel’s Repentance\u003c/h3\u003e\u003ci\u003eTo the Chief Musician. \u003ca data-toggle=\"tooltip\" data-placement=\"bottom\" title=\"Ps. 8:title\"\u003e⚓\u003c/a\u003eOn an instrument of Gath. A Psalm of Asaph.\u003c/i\u003e\u003c/div\u003e\n\u003cspan class=\"verse thi_81_1\"\u003e  \u003csup\u003e1\u003c/sup\u003eSing aloud to God our strength;\u003cbr/\u003e   Make a joyful shout to the God of Jacob.\u003cbr/\u003e\u003c/span\u003e\n\u003cspan class=\"verse thi_81_2\"\u003e   \u003csup\u003e2\u003c/sup\u003eRaise a song and strike the timbrel,\u003cbr/\u003e   The pleasant harp with the lute.\u003cbr/\u003e\u003c/span\u003e\n\u003cspan class=\"verse thi_81_3\"\u003e  \u003csup\u003e3\u003c/sup\u003eBlow the trumpet at the time of the New Moon,\u003cbr/\u003e   At the full moon, on our solemn feast day.\u003cbr/\u003e\u003c/span\u003e\n\u003cspan class=\"verse thi_81_4\"\u003e   \u003csup\u003e4\u003c/sup\u003eFor \u003ca data-toggle=\"tooltip\" data-placement=\"bottom\" title=\"Lev. 23:24; Num. 10:10\"\u003e⚓\u003c/a\u003ethis \u003ci\u003eis\u003c/i\u003e a statute for Israel,\u003cbr/\u003e   A law of the God of Jacob.\u003cbr/\u003e\u003c/span\u003e\n\u003cspan class=\"verse thi_81_5\"\u003e   \u003csup\u003e5\u003c/sup\u003eThis He established in Joseph \u003ci\u003eas\u003c/i\u003e a testimony,\u003cbr/\u003e   When He went throughout the land of Egypt,\u003cbr/\u003e   \u003ca data-toggle=\"tooltip\" data-placement=\"bottom\" title=\"Deut. 28:49; Ps. 114:1; Jer. 5:15\"\u003e⚓\u003c/a\u003e\u003ci\u003eWhere\u003c/i\u003e I heard a language I did not understand.\u003cbr/\u003e\u003c/span\u003e\n\u003cspan class=\"verse thi_81_6\"\u003e  \u003csup\u003e6\u003c/sup\u003e“I removed his shoulder from the burden;\u003cbr/\u003e   His hands were freed from the baskets.\u003cbr/\u003e\u003c/span\u003e\n\u003cspan class=\"verse thi_81_7\"\u003e   \u003csup\u003e7\u003c/sup\u003e\u003ca data-toggle=\"tooltip\" data-placement=\"bottom\" title=\"Ex. 2:23; 14:10; Ps. 50:15\"\u003e⚓\u003c/a\u003eYou called in trouble, and I delivered you;\u003cbr/\u003e   \u003ca data-toggle=\"tooltip\" data-placement=\"bottom\" title=\"Ex. 19:19; 20:18\"\u003e⚓\u003c/a\u003eI answered you in the secret place of thunder;\u003cbr/\u003e   I \u003ca data-toggle=\"tooltip\" data-placement=\"bottom\" title=\"Ex. 17:6, 7; Num. 20:13\"\u003e⚓\u003c/a\u003etested you at the waters of Meribah.\u003cbr/\u003e \u003ci\u003eSelah\u003c/i\u003e\u003cbr/\u003e\u003c/span\u003e\n\u003cspan class=\"verse thi_81_8\"\u003e  \u003csup\u003e8\u003c/sup\u003e“Hear,\u003ca data-toggle=\"tooltip\" data-placement=\"bottom\" title=\"(Ps. 50:7)\"\u003e⚓\u003c/a\u003e O My people, and I will admonish you!\u003cbr/\u003e   O Israel, if you will listen to Me!\u003cbr/\u003e\u003c/span\u003e\n\u003cspan class=\"verse thi_81_9\"\u003e   \u003csup\u003e9\u003c/sup\u003eThere shall be no \u003ca data-toggle=\"tooltip\" data-placement=\"bottom\" title=\"(Ex. 20:3; Deut. 5:7; 32:12); Ps. 44:20; (Is. 43:12)\"\u003e⚓\u003c/a\u003eforeign god among you;\u003cbr/\u003e   Nor shall you worship any foreign god.\u003cbr/\u003e\u003c/span\u003e\n\u003cspan class=\"verse thi_81_10\"\u003e   \u003csup\u003e10\u003c/sup\u003e\u003ca data-toggle=\"tooltip\" data-placement=\"bottom\" title=\"Ex. 20:2; Deut. 5:6\"\u003e⚓\u003c/a\u003eI \u003ci\u003eam\u003c/i\u003e the Lord your God,\u003cbr/\u003e   Who brought you out of the land of Egypt;\u003cbr/\u003e   \u003ca data-toggle=\"tooltip\" data-placement=\"bottom\" title=\"Ps. 103:5\"\u003e⚓\u003c/a\u003eOpen your mouth wide, and I will fill it.\u003cbr/\u003e\u003c/span\u003e\n\u003cspan class=\"verse thi_81_11\"\u003e  \u003csup\u003e11\u003c/sup\u003e“But My people would not heed My voice,\u003cbr/\u003e   And Israel would \u003ci\u003ehave\u003c/i\u003e\u003ca data-toggle=\"tooltip\" data-placement=\"bottom\" title=\"Ex. 32:1; Deut. 32:15\"\u003e⚓\u003c/a\u003enone of Me.\u003cbr/\u003e\u003c/span\u003e\n\u003cspan class=\"verse thi_81_12\"\u003e   \u003csup\u003e12\u003c/sup\u003e\u003ca data-toggle=\"tooltip\" data-placement=\"bottom\" title=\"(Job 8:4; Acts 7:42; Rom. 1:24, 26)\"\u003e⚓\u003c/a\u003eSo I gave them over to their own stubborn heart,\u003cbr/\u003e   To walk in their own counsels.\u003cbr/\u003e\u003c/span\u003e\n\u003cspan class=\"verse thi_81_13\"\u003e  \u003csup\u003e13\u003c/sup\u003e“Oh,\u003ca data-toggle=\"tooltip\" data-placement=\"bottom\" title=\"(Deut. 5:29; Is. 48:18)\"\u003e⚓\u003c/a\u003e that My people would listen to Me,\u003cbr/\u003e   That Israel would walk in My ways!\u003cbr/\u003e\u003c/span\u003e\n\u003cspan class=\"verse thi_81_14\"\u003e   \u003csup\u003e14\u003c/sup\u003eI would soon subdue their enemies,\u003cbr/\u003e   And turn My hand against their adversaries.\u003cbr/\u003e\u003c/span\u003e\n\u003cspan class=\"verse thi_81_15\"\u003e   \u003csup\u003e15\u003c/sup\u003e\u003ca data-toggle=\"tooltip\" data-placement=\"bottom\" title=\"Rom. 1:30\"\u003e⚓\u003c/a\u003eThe haters of the Lord would pretend submission to Him,\u003cbr/\u003e   But their fate would endure forever.\u003cbr/\u003e\u003c/span\u003e\n\u003cspan class=\"verse thi_81_16\"\u003e   \u003csup\u003e16\u003c/sup\u003eHe would \u003ca data-toggle=\"tooltip\" data-placement=\"bottom\" title=\"Deut. 32:14\"\u003e⚓\u003c/a\u003ehave fed them also with the finest of wheat;\u003cbr/\u003e   And with honey \u003ca data-toggle=\"tooltip\" data-placement=\"bottom\" title=\"Job 29:6\"\u003e⚓\u003c/a\u003efrom the rock I would have satisfied you.”\u003cbr/\u003e\u003c/span\u003e\n"
}