{
    "Translation": "NKJV",
    "group": "POETRY \u0026 WINSDOM",
    "BookName": "Job ",
    "BookNumber": 18,
    "Audio": [],
    "Content": "\n\u003cdiv class=\"title\"\u003e\u003ch1\u003e41\u003c/h1\u003e\u003c/div\u003e\n\u003cspan class=\"verse giop_41_1\"\u003e  \u003csup\u003e1\u003c/sup\u003e“Can you draw out \u003ca data-toggle=\"tooltip\" data-placement=\"bottom\" title=\"Ps. 74:14; 104:26; Is. 27:1\"\u003e⚓\u003c/a\u003eLeviathan with a hook,\u003cbr/\u003e   Or \u003ci\u003esnare\u003c/i\u003e his tongue with a line \u003ci\u003ewhich\u003c/i\u003e you lower?\u003cbr/\u003e\u003c/span\u003e\n\u003cspan class=\"verse giop_41_2\"\u003e   \u003csup\u003e2\u003c/sup\u003eCan you \u003ca data-toggle=\"tooltip\" data-placement=\"bottom\" title=\"2 Kin. 19:28; Is. 37:29\"\u003e⚓\u003c/a\u003eput a reed through his nose,\u003cbr/\u003e   Or pierce his jaw with a hook?\u003cbr/\u003e\u003c/span\u003e\n\u003cspan class=\"verse giop_41_3\"\u003e   \u003csup\u003e3\u003c/sup\u003eWill he make many supplications to you?\u003cbr/\u003e   Will he speak softly to you?\u003cbr/\u003e\u003c/span\u003e\n\u003cspan class=\"verse giop_41_4\"\u003e   \u003csup\u003e4\u003c/sup\u003eWill he make a covenant with you?\u003cbr/\u003e   Will you take him as a servant forever?\u003cbr/\u003e\u003c/span\u003e\n\u003cspan class=\"verse giop_41_5\"\u003e   \u003csup\u003e5\u003c/sup\u003eWill you play with him as \u003ci\u003ewith\u003c/i\u003e a bird,\u003cbr/\u003e   Or will you leash him for your maidens?\u003cbr/\u003e\u003c/span\u003e\n\u003cspan class=\"verse giop_41_6\"\u003e   \u003csup\u003e6\u003c/sup\u003eWill \u003ci\u003eyour\u003c/i\u003e companions make a banquet of him?\u003cbr/\u003e   Will they apportion him among the merchants?\u003cbr/\u003e\u003c/span\u003e\n\u003cspan class=\"verse giop_41_7\"\u003e   \u003csup\u003e7\u003c/sup\u003eCan you fill his skin with harpoons,\u003cbr/\u003e   Or his head with fishing spears?\u003cbr/\u003e\u003c/span\u003e\n\u003cspan class=\"verse giop_41_8\"\u003e   \u003csup\u003e8\u003c/sup\u003eLay your hand on him;\u003cbr/\u003e   Remember the battle—\u003cbr/\u003e   Never do it again!\u003cbr/\u003e\u003c/span\u003e\n\u003cspan class=\"verse giop_41_9\"\u003e   \u003csup\u003e9\u003c/sup\u003eIndeed, \u003ci\u003eany\u003c/i\u003e hope of \u003ci\u003eovercoming\u003c/i\u003e him is false;\u003cbr/\u003e   Shall \u003ci\u003eone\u003c/i\u003e \u003ci\u003enot\u003c/i\u003e be overwhelmed at the sight of him?\u003cbr/\u003e\u003c/span\u003e\n\u003cspan class=\"verse giop_41_10\"\u003e   \u003csup\u003e10\u003c/sup\u003eNo one \u003ci\u003eis\u003c/i\u003e \u003ci\u003eso\u003c/i\u003e fierce that he would dare stir him up.\u003cbr/\u003e   Who then is able to stand against Me?\u003cbr/\u003e\u003c/span\u003e\n\u003cspan class=\"verse giop_41_11\"\u003e   \u003csup\u003e11\u003c/sup\u003e\u003ca data-toggle=\"tooltip\" data-placement=\"bottom\" title=\"(Rom. 11:35)\"\u003e⚓\u003c/a\u003eWho has preceded Me, that I should pay \u003ci\u003ehim?\u003c/i\u003e\u003cbr/\u003e   \u003ca data-toggle=\"tooltip\" data-placement=\"bottom\" title=\"Ex. 19:5; (Deut. 10:14; Job 9:5–10; 26:6–14); Ps. 24:1; 50:12; 1 Cor. 10:26, 28\"\u003e⚓\u003c/a\u003eEverything under heaven is Mine.\u003cbr/\u003e\u003c/span\u003e\n\u003cspan class=\"verse giop_41_12\"\u003e  \u003csup\u003e12\u003c/sup\u003e“I will not conceal his limbs,\u003cbr/\u003e   His mighty power, or his graceful proportions.\u003cbr/\u003e\u003c/span\u003e\n\u003cspan class=\"verse giop_41_13\"\u003e   \u003csup\u003e13\u003c/sup\u003eWho can remove his outer coat?\u003cbr/\u003e   Who can approach \u003ci\u003ehim\u003c/i\u003e with a double bridle?\u003cbr/\u003e\u003c/span\u003e\n\u003cspan class=\"verse giop_41_14\"\u003e   \u003csup\u003e14\u003c/sup\u003eWho can open the doors of his face,\u003cbr/\u003e   \u003ci\u003eWith\u003c/i\u003e his terrible teeth all around?\u003cbr/\u003e\u003c/span\u003e\n\u003cspan class=\"verse giop_41_15\"\u003e   \u003csup\u003e15\u003c/sup\u003e\u003ci\u003eHis\u003c/i\u003e rows of scales are \u003ci\u003ehis\u003c/i\u003e pride,\u003cbr/\u003e   Shut up tightly \u003ci\u003eas\u003c/i\u003e \u003ci\u003ewith\u003c/i\u003e a seal;\u003cbr/\u003e\u003c/span\u003e\n\u003cspan class=\"verse giop_41_16\"\u003e   \u003csup\u003e16\u003c/sup\u003eOne is so near another\u003cbr/\u003e   That no air can come between them;\u003cbr/\u003e\u003c/span\u003e\n\u003cspan class=\"verse giop_41_17\"\u003e   \u003csup\u003e17\u003c/sup\u003eThey are joined one to another,\u003cbr/\u003e   They stick together and cannot be parted.\u003cbr/\u003e\u003c/span\u003e\n\u003cspan class=\"verse giop_41_18\"\u003e   \u003csup\u003e18\u003c/sup\u003eHis sneezings flash forth light,\u003cbr/\u003e   And his eyes \u003ci\u003eare\u003c/i\u003e like the eyelids of the morning.\u003cbr/\u003e\u003c/span\u003e\n\u003cspan class=\"verse giop_41_19\"\u003e   \u003csup\u003e19\u003c/sup\u003eOut of his mouth go burning lights;\u003cbr/\u003e   Sparks of fire shoot out.\u003cbr/\u003e\u003c/span\u003e\n\u003cspan class=\"verse giop_41_20\"\u003e   \u003csup\u003e20\u003c/sup\u003eSmoke goes out of his nostrils,\u003cbr/\u003e   As \u003ci\u003efrom\u003c/i\u003e a boiling pot and burning rushes.\u003cbr/\u003e\u003c/span\u003e\n\u003cspan class=\"verse giop_41_21\"\u003e   \u003csup\u003e21\u003c/sup\u003eHis breath kindles coals,\u003cbr/\u003e   And a flame goes out of his mouth.\u003cbr/\u003e\u003c/span\u003e\n\u003cspan class=\"verse giop_41_22\"\u003e   \u003csup\u003e22\u003c/sup\u003eStrength dwells in his neck,\u003cbr/\u003e   And sorrow dances before him.\u003cbr/\u003e\u003c/span\u003e\n\u003cspan class=\"verse giop_41_23\"\u003e   \u003csup\u003e23\u003c/sup\u003eThe folds of his flesh are joined together;\u003cbr/\u003e   They are firm on him and cannot be moved.\u003cbr/\u003e\u003c/span\u003e\n\u003cspan class=\"verse giop_41_24\"\u003e   \u003csup\u003e24\u003c/sup\u003eHis heart is as hard as stone,\u003cbr/\u003e   Even as hard as the lower \u003ci\u003emillstone.\u003c/i\u003e\u003cbr/\u003e\u003c/span\u003e\n\u003cspan class=\"verse giop_41_25\"\u003e   \u003csup\u003e25\u003c/sup\u003eWhen he raises himself up, the mighty are afraid;\u003cbr/\u003e   Because of his crashings they are beside themselves.\u003cbr/\u003e\u003c/span\u003e\n\u003cspan class=\"verse giop_41_26\"\u003e   \u003csup\u003e26\u003c/sup\u003e\u003ci\u003eThough\u003c/i\u003e the sword reaches him, it cannot avail;\u003cbr/\u003e   Nor does spear, dart, or javelin.\u003cbr/\u003e\u003c/span\u003e\n\u003cspan class=\"verse giop_41_27\"\u003e   \u003csup\u003e27\u003c/sup\u003eHe regards iron as straw,\u003cbr/\u003e   \u003ci\u003eAnd\u003c/i\u003e bronze as rotten wood.\u003cbr/\u003e\u003c/span\u003e\n\u003cspan class=\"verse giop_41_28\"\u003e   \u003csup\u003e28\u003c/sup\u003eThe arrow cannot make him flee;\u003cbr/\u003e   Slingstones become like stubble to him.\u003cbr/\u003e\u003c/span\u003e\n\u003cspan class=\"verse giop_41_29\"\u003e   \u003csup\u003e29\u003c/sup\u003eDarts are regarded as straw;\u003cbr/\u003e   He laughs at the threat of javelins.\u003cbr/\u003e\u003c/span\u003e\n\u003cspan class=\"verse giop_41_30\"\u003e   \u003csup\u003e30\u003c/sup\u003eHis undersides \u003ci\u003eare\u003c/i\u003e like sharp potsherds;\u003cbr/\u003e   He spreads pointed \u003ci\u003emarks\u003c/i\u003e in the mire.\u003cbr/\u003e\u003c/span\u003e\n\u003cspan class=\"verse giop_41_31\"\u003e   \u003csup\u003e31\u003c/sup\u003eHe makes the deep boil like a pot;\u003cbr/\u003e   He makes the sea like a pot of ointment.\u003cbr/\u003e\u003c/span\u003e\n\u003cspan class=\"verse giop_41_32\"\u003e   \u003csup\u003e32\u003c/sup\u003eHe leaves a shining wake behind him;\u003cbr/\u003e   \u003ci\u003eOne\u003c/i\u003e would think the deep had white hair.\u003cbr/\u003e\u003c/span\u003e\n\u003cspan class=\"verse giop_41_33\"\u003e   \u003csup\u003e33\u003c/sup\u003eOn earth there is nothing like him,\u003cbr/\u003e   Which is made without fear.\u003cbr/\u003e\u003c/span\u003e\n\u003cspan class=\"verse giop_41_34\"\u003e   \u003csup\u003e34\u003c/sup\u003eHe beholds every high \u003ci\u003ething;\u003c/i\u003e\u003cbr/\u003e   He \u003ci\u003eis\u003c/i\u003e king over all the children of pride.”\u003cbr/\u003e\u003c/span\u003e\n"
}