{
    "Translation": "NKJV",
    "group": "LAW",
    "BookName": "Exodus ",
    "BookNumber": 2,
    "Audio": [],
    "Content": "\n\u003cdiv class=\"title\"\u003e\u003ch1\u003e3\u003c/h1\u003e\u003ch3\u003eMoses at the Burning Bush\u003c/h3\u003e\u003c/div\u003e\n\u003cspan class=\"verse xu_3_1\"\u003e \u003csup\u003e1\u003c/sup\u003eNow Moses was tending the flock of \u003ca data-toggle=\"tooltip\" data-placement=\"bottom\" title=\"Ex. 4:18\"\u003e⚓\u003c/a\u003eJethro his father-in-law, \u003ca data-toggle=\"tooltip\" data-placement=\"bottom\" title=\"Ex. 2:16\"\u003e⚓\u003c/a\u003ethe priest of Midian. And he led the flock to the back of the desert, and came to \u003ca data-toggle=\"tooltip\" data-placement=\"bottom\" title=\"Ex. 17:6; 1 Kin. 19:8\"\u003e⚓\u003c/a\u003eHoreb, \u003ca data-toggle=\"tooltip\" data-placement=\"bottom\" title=\"Ex. 18:5\"\u003e⚓\u003c/a\u003ethe mountain of God. \u003c/span\u003e\n\u003cspan class=\"verse xu_3_2\"\u003e\u003csup\u003e2\u003c/sup\u003eAnd \u003ca data-toggle=\"tooltip\" data-placement=\"bottom\" title=\"Deut. 33:16; Mark 12:26; Luke 20:37; Acts 7:30\"\u003e⚓\u003c/a\u003ethe Angel of the Lord appeared to him in a flame of fire from the midst of a bush. So he looked, and behold, the bush was burning with fire, but the bush \u003ci\u003ewas\u003c/i\u003e not consumed. \u003c/span\u003e\n\u003cspan class=\"verse xu_3_3\"\u003e\u003csup\u003e3\u003c/sup\u003eThen Moses said, “I will now turn aside and see this \u003ca data-toggle=\"tooltip\" data-placement=\"bottom\" title=\"Acts 7:31\"\u003e⚓\u003c/a\u003egreat sight, why the bush does not burn.”\u003cbr/\u003e\u003c/span\u003e\n\u003cspan class=\"verse xu_3_4\"\u003e \u003csup\u003e4\u003c/sup\u003eSo when the Lord saw that he turned aside to look, God called \u003ca data-toggle=\"tooltip\" data-placement=\"bottom\" title=\"Ex. 4:5; Deut. 33:16\"\u003e⚓\u003c/a\u003eto him from the midst of the bush and said, “Moses, Moses!”\u003cbr/\u003e And he said, “Here I am.”\u003cbr/\u003e\u003c/span\u003e\n\u003cspan class=\"verse xu_3_5\"\u003e \u003csup\u003e5\u003c/sup\u003eThen He said, “Do not draw near this place. \u003ca data-toggle=\"tooltip\" data-placement=\"bottom\" title=\"Josh. 5:15; Acts 7:33\"\u003e⚓\u003c/a\u003eTake your sandals off your feet, for the place where you stand \u003ci\u003eis\u003c/i\u003e holy ground.” \u003c/span\u003e\n\u003cspan class=\"verse xu_3_6\"\u003e\u003csup\u003e6\u003c/sup\u003eMoreover He said, \u003ca data-toggle=\"tooltip\" data-placement=\"bottom\" title=\"Gen. 28:13; Ex. 3:16; 4:5; (Matt. 22:32; Mark 12:26, 27; Luke 20:37, 38); Acts 7:32\"\u003e⚓\u003c/a\u003e“I \u003ci\u003eam\u003c/i\u003e the God of your father—the God of Abraham, the God of Isaac, and the God of Jacob.” And Moses hid his face, for \u003ca data-toggle=\"tooltip\" data-placement=\"bottom\" title=\"1 Kin. 19:13\"\u003e⚓\u003c/a\u003ehe was afraid to look upon God.\u003cbr/\u003e\u003c/span\u003e\n\u003cspan class=\"verse xu_3_7\"\u003e \u003csup\u003e7\u003c/sup\u003eAnd the Lord said: \u003ca data-toggle=\"tooltip\" data-placement=\"bottom\" title=\"Ex. 2:23–25; Neh. 9:9; Ps. 106:44\"\u003e⚓\u003c/a\u003e“I have surely seen the oppression of My people who \u003ci\u003eare\u003c/i\u003e in Egypt, and have heard their cry \u003ca data-toggle=\"tooltip\" data-placement=\"bottom\" title=\"Ex. 1:11\"\u003e⚓\u003c/a\u003ebecause of their taskmasters, \u003ca data-toggle=\"tooltip\" data-placement=\"bottom\" title=\"Gen. 18:21; Ex. 2:25\"\u003e⚓\u003c/a\u003efor I know their sorrows. \u003c/span\u003e\n\u003cspan class=\"verse xu_3_8\"\u003e\u003csup\u003e8\u003c/sup\u003eSo \u003ca data-toggle=\"tooltip\" data-placement=\"bottom\" title=\"Gen. 15:13–16; 46:4; 50:24, 25\"\u003e⚓\u003c/a\u003eI have come down to \u003ca data-toggle=\"tooltip\" data-placement=\"bottom\" title=\"Ex. 6:6–8; 12:51\"\u003e⚓\u003c/a\u003edeliver them out of the hand of the Egyptians, and to bring them up from that land to \u003ca data-toggle=\"tooltip\" data-placement=\"bottom\" title=\"Num. 13:27; Deut. 1:25; 8:7–9; Josh. 3:17\"\u003e⚓\u003c/a\u003ea good and large land, to a land \u003ca data-toggle=\"tooltip\" data-placement=\"bottom\" title=\"Ex. 3:17; 13:5; Jer. 11:5; Ezek. 20:6\"\u003e⚓\u003c/a\u003eflowing with milk and honey, to the place of \u003ca data-toggle=\"tooltip\" data-placement=\"bottom\" title=\"Gen. 15:19–21; Josh. 24:11\"\u003e⚓\u003c/a\u003ethe Canaanites and the Hittites and the Amorites and the Perizzites and the Hivites and the Jebusites. \u003c/span\u003e\n\u003cspan class=\"verse xu_3_9\"\u003e\u003csup\u003e9\u003c/sup\u003eNow therefore, behold, \u003ca data-toggle=\"tooltip\" data-placement=\"bottom\" title=\"Ex. 2:23\"\u003e⚓\u003c/a\u003ethe cry of the children of Israel has come to Me, and I have also seen the \u003ca data-toggle=\"tooltip\" data-placement=\"bottom\" title=\"Ex. 1:11, 13, 14\"\u003e⚓\u003c/a\u003eoppression with which the Egyptians oppress them. \u003c/span\u003e\n\u003cspan class=\"verse xu_3_10\"\u003e\u003csup\u003e10\u003c/sup\u003e\u003ca data-toggle=\"tooltip\" data-placement=\"bottom\" title=\"Gen. 15:13, 14; Ex. 12:40, 41; (Mic. 6:4); Acts 7:6, 7\"\u003e⚓\u003c/a\u003eCome now, therefore, and I will send you to Pharaoh that you may bring My people, the children of Israel, out of Egypt.”\u003cbr/\u003e\u003c/span\u003e\n\u003cspan class=\"verse xu_3_11\"\u003e \u003csup\u003e11\u003c/sup\u003eBut Moses said to God, \u003ca data-toggle=\"tooltip\" data-placement=\"bottom\" title=\"Ex. 4:10; 6:12; 1 Sam. 18:18\"\u003e⚓\u003c/a\u003e“Who \u003ci\u003eam\u003c/i\u003e I that I should go to Pharaoh, and that I should bring the children of Israel out of Egypt?”\u003cbr/\u003e\u003c/span\u003e\n\u003cspan class=\"verse xu_3_12\"\u003e \u003csup\u003e12\u003c/sup\u003eSo He said, \u003ca data-toggle=\"tooltip\" data-placement=\"bottom\" title=\"Gen. 31:3; Ex. 4:12, 15; 33:14–16; Deut. 31:23; Josh. 1:5; Is. 43:2; Rom. 8:31\"\u003e⚓\u003c/a\u003e“I will certainly be with you. And this \u003ci\u003eshall\u003c/i\u003e \u003ci\u003ebe\u003c/i\u003e a \u003ca data-toggle=\"tooltip\" data-placement=\"bottom\" title=\"Ex. 4:8; 19:3\"\u003e⚓\u003c/a\u003esign to you that I have sent you: When you have brought the people out of Egypt, you shall serve God on this mountain.”\u003cbr/\u003e\u003c/span\u003e\n\u003cspan class=\"verse xu_3_13\"\u003e \u003csup\u003e13\u003c/sup\u003eThen Moses said to God, “Indeed, \u003ci\u003ewhen\u003c/i\u003e I come to the children of Israel and say to them, ‘The God of your fathers has sent me to you,’ and they say to me, ‘What \u003ci\u003eis\u003c/i\u003e His name?’ what shall I say to them?”\u003cbr/\u003e\u003c/span\u003e\n\u003cspan class=\"verse xu_3_14\"\u003e \u003csup\u003e14\u003c/sup\u003eAnd God said to Moses, “I AM WHO I AM.” And He said, “Thus you shall say to the children of Israel, \u003ca data-toggle=\"tooltip\" data-placement=\"bottom\" title=\"(Ex. 6:3; John 8:24, 28, 58; Heb. 13:8; Rev. 1:8; 4:8)\"\u003e⚓\u003c/a\u003e‘I AM has sent me to you.’ ” \u003c/span\u003e\n\u003cspan class=\"verse xu_3_15\"\u003e\u003csup\u003e15\u003c/sup\u003eMoreover God said to Moses, “Thus you shall say to the children of Israel: ‘The Lord God of your fathers, the God of Abraham, the God of Isaac, and the God of Jacob, has sent me to you. This \u003ci\u003eis\u003c/i\u003e\u003ca data-toggle=\"tooltip\" data-placement=\"bottom\" title=\"Ps. 30:4; 97:12; 102:12; 135:13; (Hos. 12:5)\"\u003e⚓\u003c/a\u003eMy name forever, and this \u003ci\u003eis\u003c/i\u003e My memorial to all generations.’ \u003c/span\u003e\n\u003cspan class=\"verse xu_3_16\"\u003e\u003csup\u003e16\u003c/sup\u003eGo and \u003ca data-toggle=\"tooltip\" data-placement=\"bottom\" title=\"Ex. 4:29\"\u003e⚓\u003c/a\u003egather the elders of Israel together, and say to them, ‘The Lord God of your fathers, the God of Abraham, of Isaac, and of Jacob, appeared to me, saying, \u003ca data-toggle=\"tooltip\" data-placement=\"bottom\" title=\"Gen. 50:24; Ex. 2:25; 4:31; Ps. 33:18; Luke 1:68\"\u003e⚓\u003c/a\u003e“I have surely visited you and \u003ci\u003eseen\u003c/i\u003e what is done to you in Egypt; \u003c/span\u003e\n\u003cspan class=\"verse xu_3_17\"\u003e\u003csup\u003e17\u003c/sup\u003eand I have said \u003ca data-toggle=\"tooltip\" data-placement=\"bottom\" title=\"Gen. 15:13–21; 46:4; 50:24, 25\"\u003e⚓\u003c/a\u003eI will bring you up out of the affliction of Egypt to the land of the Canaanites and the Hittites and the Amorites and the Perizzites and the Hivites and the Jebusites, to a land flowing with milk and honey.” ’ \u003c/span\u003e\n\u003cspan class=\"verse xu_3_18\"\u003e\u003csup\u003e18\u003c/sup\u003eThen \u003ca data-toggle=\"tooltip\" data-placement=\"bottom\" title=\"Ex. 4:31\"\u003e⚓\u003c/a\u003ethey will heed your voice; and \u003ca data-toggle=\"tooltip\" data-placement=\"bottom\" title=\"Ex. 5:1, 3\"\u003e⚓\u003c/a\u003eyou shall come, you and the elders of Israel, to the king of Egypt; and you shall say to him, ‘The Lord God of the Hebrews has \u003ca data-toggle=\"tooltip\" data-placement=\"bottom\" title=\"Num. 23:3, 4, 15, 16\"\u003e⚓\u003c/a\u003emet with us; and now, please, let us go three days’ journey into the wilderness, that we may sacrifice to the Lord our God.’ \u003c/span\u003e\n\u003cspan class=\"verse xu_3_19\"\u003e\u003csup\u003e19\u003c/sup\u003eBut I am sure that the king of Egypt \u003ca data-toggle=\"tooltip\" data-placement=\"bottom\" title=\"Ex. 5:2\"\u003e⚓\u003c/a\u003ewill not let you go, no, not even by a mighty hand. \u003c/span\u003e\n\u003cspan class=\"verse xu_3_20\"\u003e\u003csup\u003e20\u003c/sup\u003eSo I will \u003ca data-toggle=\"tooltip\" data-placement=\"bottom\" title=\"Ex. 6:6; 9:15\"\u003e⚓\u003c/a\u003estretch out My hand and strike Egypt with \u003ca data-toggle=\"tooltip\" data-placement=\"bottom\" title=\"Deut. 6:22; Neh. 9:10; Ps. 105:27; 135:9; Jer. 32:20; Acts 7:36\"\u003e⚓\u003c/a\u003eall My wonders which I will do in its midst; and \u003ca data-toggle=\"tooltip\" data-placement=\"bottom\" title=\"Ex. 11:1; 12:31–37\"\u003e⚓\u003c/a\u003eafter that he will let you go. \u003c/span\u003e\n\u003cspan class=\"verse xu_3_21\"\u003e\u003csup\u003e21\u003c/sup\u003eAnd \u003ca data-toggle=\"tooltip\" data-placement=\"bottom\" title=\"Ex. 11:3; 12:36; 1 Kin. 8:50; Ps. 105:37; 106:46; (Prov. 16:7)\"\u003e⚓\u003c/a\u003eI will give this people favor in the sight of the Egyptians; and it shall be, when you go, that you shall not go empty-handed. \u003c/span\u003e\n\u003cspan class=\"verse xu_3_22\"\u003e\u003csup\u003e22\u003c/sup\u003e\u003ca data-toggle=\"tooltip\" data-placement=\"bottom\" title=\"Ex. 11:2\"\u003e⚓\u003c/a\u003eBut every woman shall ask of her neighbor, namely, of her who dwells near her house, \u003ca data-toggle=\"tooltip\" data-placement=\"bottom\" title=\"Ex. 33:6\"\u003e⚓\u003c/a\u003earticles of silver, articles of gold, and clothing; and you shall put \u003ci\u003ethem\u003c/i\u003e on your sons and on your daughters. So \u003ca data-toggle=\"tooltip\" data-placement=\"bottom\" title=\"Job 27:17; Prov. 13:22; (Ezek. 39:10)\"\u003e⚓\u003c/a\u003eyou shall plunder the Egyptians.”\u003cbr/\u003e\u003c/span\u003e\n"
}